<?xml version="1.0" encoding="utf-8"?>
<DeviceDictionary xmlns:xsi="http://www.w3.org/2001/XMLSchema-instance" xmlns:xsd="http://www.w3.org/2001/XMLSchema">
  <Name>Плата термодатчиков</Name>
  <GenItems>
    <DeviceDictionaryROItem>
      <Bits>16</Bits>
      <Use>true</Use>
      <Name>ID устройства</Name>
      <ShowFunction>ShowHex4</ShowFunction>
    </DeviceDictionaryROItem>
    <DeviceDictionaryROItem>
      <Bits>16</Bits>
      <Use>true</Use>
      <Name>Версия</Name>
      <ShowFunction>ShowVersion</ShowFunction>
    </DeviceDictionaryROItem>
    <DeviceDictionaryROItem>
      <Bits>16</Bits>
      <Use>true</Use>
      <Name>hashcode</Name>
      <ShowFunction>ShowHex4</ShowFunction>
    </DeviceDictionaryROItem>
    <DeviceDictionaryROItem>
      <Bits>16</Bits>
      <Use>true</Use>
      <Name>Размер RO</Name>
      <ShowFunction>ShowUInt</ShowFunction>
    </DeviceDictionaryROItem>
    <DeviceDictionaryROItem>
      <Bits>16</Bits>
      <Use>true</Use>
      <Name>Размер RW</Name>
      <ShowFunction>ShowUInt</ShowFunction>
    </DeviceDictionaryROItem>
    <DeviceDictionaryROItem>
      <Bits>16</Bits>
      <Use>true</Use>
      <Name>Размер ROM</Name>
      <ShowFunction>ShowUInt</ShowFunction>
    </DeviceDictionaryROItem>
  </GenItems>
  <ROItems>
    <DeviceDictionaryROItem>
      <Bits>16</Bits>
      <Use>true</Use>
      <Name>Температура А01</Name>
      <ShowFunction>ShowTemperature_x10</ShowFunction>
    </DeviceDictionaryROItem>
    <DeviceDictionaryROItem>
      <Bits>16</Bits>
      <Use>true</Use>
      <Name>Температура А02</Name>
      <ShowFunction>ShowTemperature_x10</ShowFunction>
    </DeviceDictionaryROItem>
    <DeviceDictionaryROItem>
      <Bits>16</Bits>
      <Use>true</Use>
      <Name>Температура А03</Name>
      <ShowFunction>ShowTemperature_x10</ShowFunction>
    </DeviceDictionaryROItem>
    <DeviceDictionaryROItem>
      <Bits>16</Bits>
      <Use>true</Use>
      <Name>Температура А04</Name>
      <ShowFunction>ShowTemperature_x10</ShowFunction>
    </DeviceDictionaryROItem>
    <DeviceDictionaryROItem>
      <Bits>16</Bits>
      <Use>true</Use>
      <Name>Температура А05</Name>
      <ShowFunction>ShowTemperature_x10</ShowFunction>
    </DeviceDictionaryROItem>
    <DeviceDictionaryROItem>
      <Bits>16</Bits>
      <Use>true</Use>
      <Name>Температура А06</Name>
      <ShowFunction>ShowTemperature_x10</ShowFunction>
    </DeviceDictionaryROItem>
    <DeviceDictionaryROItem>
      <Bits>16</Bits>
      <Use>true</Use>
      <Name>Температура А07</Name>
      <ShowFunction>ShowTemperature_x10</ShowFunction>
    </DeviceDictionaryROItem>
    <DeviceDictionaryROItem>
      <Bits>16</Bits>
      <Use>true</Use>
      <Name>Температура А08</Name>
      <ShowFunction>ShowTemperature_x10</ShowFunction>
    </DeviceDictionaryROItem>
    <DeviceDictionaryROItem>
      <Bits>16</Bits>
      <Use>true</Use>
      <Name>Температура А09</Name>
      <ShowFunction>ShowTemperature_x10</ShowFunction>
    </DeviceDictionaryROItem>
    <DeviceDictionaryROItem>
      <Bits>16</Bits>
      <Use>true</Use>
      <Name>Температура А10</Name>
      <ShowFunction>ShowTemperature_x10</ShowFunction>
    </DeviceDictionaryROItem>
    <DeviceDictionaryROItem>
      <Bits>16</Bits>
      <Use>true</Use>
      <Name>Температура А11</Name>
      <ShowFunction>ShowTemperature_x10</ShowFunction>
    </DeviceDictionaryROItem>
    <DeviceDictionaryROItem>
      <Bits>16</Bits>
      <Use>true</Use>
      <Name>Температура А12</Name>
      <ShowFunction>ShowTemperature_x10</ShowFunction>
    </DeviceDictionaryROItem>
    <DeviceDictionaryROItem>
      <Bits>16</Bits>
      <Use>true</Use>
      <Name>Температура А13</Name>
      <ShowFunction>ShowTemperature_x10</ShowFunction>
    </DeviceDictionaryROItem>
    <DeviceDictionaryROItem>
      <Bits>16</Bits>
      <Use>true</Use>
      <Name>Температура А14</Name>
      <ShowFunction>ShowTemperature_x10</ShowFunction>
    </DeviceDictionaryROItem>
    <DeviceDictionaryROItem>
      <Bits>16</Bits>
      <Use>true</Use>
      <Name>Температура А15</Name>
      <ShowFunction>ShowTemperature_x10</ShowFunction>
    </DeviceDictionaryROItem>
    <DeviceDictionaryROItem>
      <Bits>16</Bits>
      <Use>true</Use>
      <Name>Температура А16</Name>
      <ShowFunction>ShowTemperature_x10</ShowFunction>
    </DeviceDictionaryROItem>
    <DeviceDictionaryROItem>
      <Bits>16</Bits>
      <Use>true</Use>
      <Name>Температура Б01</Name>
      <ShowFunction>ShowTemperature_x10</ShowFunction>
    </DeviceDictionaryROItem>
    <DeviceDictionaryROItem>
      <Bits>16</Bits>
      <Use>true</Use>
      <Name>Температура Б02</Name>
      <ShowFunction>ShowTemperature_x10</ShowFunction>
    </DeviceDictionaryROItem>
    <DeviceDictionaryROItem>
      <Bits>16</Bits>
      <Use>true</Use>
      <Name>Температура Б03</Name>
      <ShowFunction>ShowTemperature_x10</ShowFunction>
    </DeviceDictionaryROItem>
    <DeviceDictionaryROItem>
      <Bits>16</Bits>
      <Use>true</Use>
      <Name>Температура Б04</Name>
      <ShowFunction>ShowTemperature_x10</ShowFunction>
    </DeviceDictionaryROItem>
    <DeviceDictionaryROItem>
      <Bits>16</Bits>
      <Use>true</Use>
      <Name>Температура Б05</Name>
      <ShowFunction>ShowTemperature_x10</ShowFunction>
    </DeviceDictionaryROItem>
    <DeviceDictionaryROItem>
      <Bits>16</Bits>
      <Use>true</Use>
      <Name>Температура Б06</Name>
      <ShowFunction>ShowTemperature_x10</ShowFunction>
    </DeviceDictionaryROItem>
    <DeviceDictionaryROItem>
      <Bits>16</Bits>
      <Use>true</Use>
      <Name>Температура Б07</Name>
      <ShowFunction>ShowTemperature_x10</ShowFunction>
    </DeviceDictionaryROItem>
    <DeviceDictionaryROItem>
      <Bits>16</Bits>
      <Use>true</Use>
      <Name>Температура Б08</Name>
      <ShowFunction>ShowTemperature_x10</ShowFunction>
    </DeviceDictionaryROItem>
    <DeviceDictionaryROItem>
      <Bits>16</Bits>
      <Use>true</Use>
      <Name>Температура Б09</Name>
      <ShowFunction>ShowTemperature_x10</ShowFunction>
    </DeviceDictionaryROItem>
    <DeviceDictionaryROItem>
      <Bits>16</Bits>
      <Use>true</Use>
      <Name>Температура Б10</Name>
      <ShowFunction>ShowTemperature_x10</ShowFunction>
    </DeviceDictionaryROItem>
    <DeviceDictionaryROItem>
      <Bits>16</Bits>
      <Use>true</Use>
      <Name>Температура Б11</Name>
      <ShowFunction>ShowTemperature_x10</ShowFunction>
    </DeviceDictionaryROItem>
    <DeviceDictionaryROItem>
      <Bits>16</Bits>
      <Use>true</Use>
      <Name>Температура Б12</Name>
      <ShowFunction>ShowTemperature_x10</ShowFunction>
    </DeviceDictionaryROItem>
    <DeviceDictionaryROItem>
      <Bits>16</Bits>
      <Use>true</Use>
      <Name>Температура Б13</Name>
      <ShowFunction>ShowTemperature_x10</ShowFunction>
    </DeviceDictionaryROItem>
    <DeviceDictionaryROItem>
      <Bits>16</Bits>
      <Use>true</Use>
      <Name>Температура Б14</Name>
      <ShowFunction>ShowTemperature_x10</ShowFunction>
    </DeviceDictionaryROItem>
    <DeviceDictionaryROItem>
      <Bits>16</Bits>
      <Use>true</Use>
      <Name>Температура Б15</Name>
      <ShowFunction>ShowTemperature_x10</ShowFunction>
    </DeviceDictionaryROItem>
    <DeviceDictionaryROItem>
      <Bits>16</Bits>
      <Use>true</Use>
      <Name>Температура Б16</Name>
      <ShowFunction>ShowTemperature_x10</ShowFunction>
    </DeviceDictionaryROItem>
    <DeviceDictionaryROItem>
      <Bits>16</Bits>
      <Use>true</Use>
      <Name>Неудачное чтение А</Name>
      <ShowFunction>ShowHex4</ShowFunction>
    </DeviceDictionaryROItem>
    <DeviceDictionaryROItem>
      <Bits>16</Bits>
      <Use>true</Use>
      <Name>Неудачное чтение Б</Name>
      <ShowFunction>ShowHex4</ShowFunction>
    </DeviceDictionaryROItem>
    <DeviceDictionaryROItem>
      <Bits>16</Bits>
      <Use>true</Use>
      <Name>Маска найденных датчиков А</Name>
      <ShowFunction>ShowHex4</ShowFunction>
    </DeviceDictionaryROItem>
    <DeviceDictionaryROItem>
      <Bits>16</Bits>
      <Use>true</Use>
      <Name>Маска найденных датчиков Б</Name>
      <ShowFunction>ShowHex4</ShowFunction>
    </DeviceDictionaryROItem>
    <DeviceDictionaryROItem>
      <Bits>16</Bits>
      <Use>true</Use>
      <Name>Количество датчиков А</Name>
      <ShowFunction>ShowUInt</ShowFunction>
    </DeviceDictionaryROItem>
    <DeviceDictionaryROItem>
      <Bits>16</Bits>
      <Use>true</Use>
      <Name>Количество датчиков Б</Name>
      <ShowFunction>ShowUInt</ShowFunction>
    </DeviceDictionaryROItem>
    <DeviceDictionaryROItem>
      <Bits>16</Bits>
      <Use>true</Use>
      <Name>Регистр состояния</Name>
      <ShowFunction>ShowHex4</ShowFunction>
    </DeviceDictionaryROItem>
    <DeviceDictionaryROItem>
      <Bits>32</Bits>
      <Use>true</Use>
      <Name>Время</Name>
      <ShowFunction>ShowUInt</ShowFunction>
    </DeviceDictionaryROItem>
    <DeviceDictionaryROItem>
      <Bits>16</Bits>
      <Use>true</Use>
      <Name>ID А01</Name>
      <ShowFunction>ShowTermoId16</ShowFunction>
    </DeviceDictionaryROItem>
    <DeviceDictionaryROItem>
      <Bits>16</Bits>
      <Use>true</Use>
      <Name>ID А02</Name>
      <ShowFunction>ShowTermoId16</ShowFunction>
    </DeviceDictionaryROItem>
    <DeviceDictionaryROItem>
      <Bits>16</Bits>
      <Use>true</Use>
      <Name>ID А03</Name>
      <ShowFunction>ShowTermoId16</ShowFunction>
    </DeviceDictionaryROItem>
    <DeviceDictionaryROItem>
      <Bits>16</Bits>
      <Use>true</Use>
      <Name>ID А04</Name>
      <ShowFunction>ShowTermoId16</ShowFunction>
    </DeviceDictionaryROItem>
    <DeviceDictionaryROItem>
      <Bits>16</Bits>
      <Use>true</Use>
      <Name>ID А05</Name>
      <ShowFunction>ShowTermoId16</ShowFunction>
    </DeviceDictionaryROItem>
    <DeviceDictionaryROItem>
      <Bits>16</Bits>
      <Use>true</Use>
      <Name>ID А06</Name>
      <ShowFunction>ShowTermoId16</ShowFunction>
    </DeviceDictionaryROItem>
    <DeviceDictionaryROItem>
      <Bits>16</Bits>
      <Use>true</Use>
      <Name>ID А07</Name>
      <ShowFunction>ShowTermoId16</ShowFunction>
    </DeviceDictionaryROItem>
    <DeviceDictionaryROItem>
      <Bits>16</Bits>
      <Use>true</Use>
      <Name>ID А08</Name>
      <ShowFunction>ShowTermoId16</ShowFunction>
    </DeviceDictionaryROItem>
    <DeviceDictionaryROItem>
      <Bits>16</Bits>
      <Use>true</Use>
      <Name>ID А09</Name>
      <ShowFunction>ShowTermoId16</ShowFunction>
    </DeviceDictionaryROItem>
    <DeviceDictionaryROItem>
      <Bits>16</Bits>
      <Use>true</Use>
      <Name>ID А10</Name>
      <ShowFunction>ShowTermoId16</ShowFunction>
    </DeviceDictionaryROItem>
    <DeviceDictionaryROItem>
      <Bits>16</Bits>
      <Use>true</Use>
      <Name>ID А11</Name>
      <ShowFunction>ShowTermoId16</ShowFunction>
    </DeviceDictionaryROItem>
    <DeviceDictionaryROItem>
      <Bits>16</Bits>
      <Use>true</Use>
      <Name>ID А12</Name>
      <ShowFunction>ShowTermoId16</ShowFunction>
    </DeviceDictionaryROItem>
    <DeviceDictionaryROItem>
      <Bits>16</Bits>
      <Use>true</Use>
      <Name>ID А13</Name>
      <ShowFunction>ShowTermoId16</ShowFunction>
    </DeviceDictionaryROItem>
    <DeviceDictionaryROItem>
      <Bits>16</Bits>
      <Use>true</Use>
      <Name>ID А14</Name>
      <ShowFunction>ShowTermoId16</ShowFunction>
    </DeviceDictionaryROItem>
    <DeviceDictionaryROItem>
      <Bits>16</Bits>
      <Use>true</Use>
      <Name>ID А15</Name>
      <ShowFunction>ShowTermoId16</ShowFunction>
    </DeviceDictionaryROItem>
    <DeviceDictionaryROItem>
      <Bits>16</Bits>
      <Use>true</Use>
      <Name>ID А16</Name>
      <ShowFunction>ShowTermoId16</ShowFunction>
    </DeviceDictionaryROItem>
    <DeviceDictionaryROItem>
      <Bits>16</Bits>
      <Use>true</Use>
      <Name>ID Б01</Name>
      <ShowFunction>ShowTermoId16</ShowFunction>
    </DeviceDictionaryROItem>
    <DeviceDictionaryROItem>
      <Bits>16</Bits>
      <Use>true</Use>
      <Name>ID Б02</Name>
      <ShowFunction>ShowTermoId16</ShowFunction>
    </DeviceDictionaryROItem>
    <DeviceDictionaryROItem>
      <Bits>16</Bits>
      <Use>true</Use>
      <Name>ID Б03</Name>
      <ShowFunction>ShowTermoId16</ShowFunction>
    </DeviceDictionaryROItem>
    <DeviceDictionaryROItem>
      <Bits>16</Bits>
      <Use>true</Use>
      <Name>ID Б04</Name>
      <ShowFunction>ShowTermoId16</ShowFunction>
    </DeviceDictionaryROItem>
    <DeviceDictionaryROItem>
      <Bits>16</Bits>
      <Use>true</Use>
      <Name>ID Б05</Name>
      <ShowFunction>ShowTermoId16</ShowFunction>
    </DeviceDictionaryROItem>
    <DeviceDictionaryROItem>
      <Bits>16</Bits>
      <Use>true</Use>
      <Name>ID Б06</Name>
      <ShowFunction>ShowTermoId16</ShowFunction>
    </DeviceDictionaryROItem>
    <DeviceDictionaryROItem>
      <Bits>16</Bits>
      <Use>true</Use>
      <Name>ID Б07</Name>
      <ShowFunction>ShowTermoId16</ShowFunction>
    </DeviceDictionaryROItem>
    <DeviceDictionaryROItem>
      <Bits>16</Bits>
      <Use>true</Use>
      <Name>ID Б08</Name>
      <ShowFunction>ShowTermoId16</ShowFunction>
    </DeviceDictionaryROItem>
    <DeviceDictionaryROItem>
      <Bits>16</Bits>
      <Use>true</Use>
      <Name>ID Б09</Name>
      <ShowFunction>ShowTermoId16</ShowFunction>
    </DeviceDictionaryROItem>
    <DeviceDictionaryROItem>
      <Bits>16</Bits>
      <Use>true</Use>
      <Name>ID Б10</Name>
      <ShowFunction>ShowTermoId16</ShowFunction>
    </DeviceDictionaryROItem>
    <DeviceDictionaryROItem>
      <Bits>16</Bits>
      <Use>true</Use>
      <Name>ID Б11</Name>
      <ShowFunction>ShowTermoId16</ShowFunction>
    </DeviceDictionaryROItem>
    <DeviceDictionaryROItem>
      <Bits>16</Bits>
      <Use>true</Use>
      <Name>ID Б12</Name>
      <ShowFunction>ShowTermoId16</ShowFunction>
    </DeviceDictionaryROItem>
    <DeviceDictionaryROItem>
      <Bits>16</Bits>
      <Use>true</Use>
      <Name>ID Б13</Name>
      <ShowFunction>ShowTermoId16</ShowFunction>
    </DeviceDictionaryROItem>
    <DeviceDictionaryROItem>
      <Bits>16</Bits>
      <Use>true</Use>
      <Name>ID Б14</Name>
      <ShowFunction>ShowTermoId16</ShowFunction>
    </DeviceDictionaryROItem>
    <DeviceDictionaryROItem>
      <Bits>16</Bits>
      <Use>true</Use>
      <Name>ID Б15</Name>
      <ShowFunction>ShowTermoId16</ShowFunction>
    </DeviceDictionaryROItem>
    <DeviceDictionaryROItem>
      <Bits>16</Bits>
      <Use>true</Use>
      <Name>ID Б16</Name>
      <ShowFunction>ShowTermoId16</ShowFunction>
    </DeviceDictionaryROItem>
  </ROItems>
  <RWItems>
    <DeviceDictionaryRWItem>
      <Bits>8</Bits>
      <Use>true</Use>
      <Name>Номер программируемого датчика в списке определенных</Name>
      <ShowFunction>ShowUInt</ShowFunction>
      <ParseFunction>ParseUInt</ParseFunction>
    </DeviceDictionaryRWItem>
    <DeviceDictionaryRWItem>
      <Bits>8</Bits>
      <Use>true</Use>
      <Name>Канал программируемого датчика(А = 0, Б = 1)</Name>
      <ShowFunction>ShowUInt</ShowFunction>
      <ParseFunction>ParseUInt</ParseFunction>
    </DeviceDictionaryRWItem>
    <DeviceDictionaryRWItem>
      <Bits>15</Bits>
      <Use>true</Use>
      <Name>Новый ID</Name>
      <ShowFunction>ShowUInt</ShowFunction>
      <ParseFunction>ParseUInt</ParseFunction>
    </DeviceDictionaryRWItem>
    <DeviceDictionaryRWItem>
      <Bits>1</Bits>
      <Use>true</Use>
      <Name>Прошить?(0 - нет, 1 - да)</Name>
      <ShowFunction>ShowUInt</ShowFunction>
      <ParseFunction>ParseUInt</ParseFunction>
    </DeviceDictionaryRWItem>
  </RWItems>
  <RWFlashItems>
    <DeviceDictionaryRWItem>
      <Bits>16</Bits>
      <Use>true</Use>
      <Name>Сетевой ID</Name>
      <ShowFunction>ShowHex4</ShowFunction>
      <ParseFunction>ParseUIntHex</ParseFunction>
    </DeviceDictionaryRWItem>
    <DeviceDictionaryRWItem>
      <Bits>16</Bits>
      <Use>true</Use>
      <Name>Задержка отправки RS-485</Name>
      <ShowFunction>ShowUInt</ShowFunction>
      <ParseFunction>ParseUInt</ParseFunction>
    </DeviceDictionaryRWItem>
    <DeviceDictionaryRWItem>
      <Bits>16</Bits>
      <Use>false</Use>
      <Name>Вспомог. слово</Name>
      <ShowFunction>ShowHex4</ShowFunction>
      <ParseFunction>ParseUIntHex</ParseFunction>
    </DeviceDictionaryRWItem>
    <DeviceDictionaryRWItem>
      <Bits>16</Bits>
      <Use>true</Use>
      <Name>Разрешить короткие ответы RS-485</Name>
      <ShowFunction>ShowUInt</ShowFunction>
      <ParseFunction>ParseUInt</ParseFunction>
    </DeviceDictionaryRWItem>
    <DeviceDictionaryRWItem>
      <Bits>16</Bits>
      <Use>false</Use>
      <Name>Параметр 4</Name>
      <ShowFunction>ShowUInt</ShowFunction>
      <ParseFunction>ParseUInt</ParseFunction>
    </DeviceDictionaryRWItem>
    <DeviceDictionaryRWItem>
      <Bits>16</Bits>
      <Use>false</Use>
      <Name>Параметр 5</Name>
      <ShowFunction>ShowUInt</ShowFunction>
      <ParseFunction>ParseUInt</ParseFunction>
    </DeviceDictionaryRWItem>
    <DeviceDictionaryRWItem>
      <Bits>16</Bits>
      <Use>false</Use>
      <Name>Параметр 6</Name>
      <ShowFunction>ShowUInt</ShowFunction>
      <ParseFunction>ParseUInt</ParseFunction>
    </DeviceDictionaryRWItem>
    <DeviceDictionaryRWItem>
      <Bits>16</Bits>
      <Use>false</Use>
      <Name>Параметр 7</Name>
      <ShowFunction>ShowUInt</ShowFunction>
      <ParseFunction>ParseUInt</ParseFunction>
    </DeviceDictionaryRWItem>
    <DeviceDictionaryRWItem>
      <Bits>16</Bits>
      <Use>false</Use>
      <Name>Параметр 8</Name>
      <ShowFunction>ShowUInt</ShowFunction>
      <ParseFunction>ParseUInt</ParseFunction>
    </DeviceDictionaryRWItem>
    <DeviceDictionaryRWItem>
      <Bits>16</Bits>
      <Use>false</Use>
      <Name>Параметр 9</Name>
      <ShowFunction>ShowUInt</ShowFunction>
      <ParseFunction>ParseUInt</ParseFunction>
    </DeviceDictionaryRWItem>
    <DeviceDictionaryRWItem>
      <Bits>16</Bits>
      <Use>false</Use>
      <Name>Параметр 10</Name>
      <ShowFunction>ShowUInt</ShowFunction>
      <ParseFunction>ParseUInt</ParseFunction>
    </DeviceDictionaryRWItem>
    <DeviceDictionaryRWItem>
      <Bits>16</Bits>
      <Use>false</Use>
      <Name>Параметр 11</Name>
      <ShowFunction>ShowUInt</ShowFunction>
      <ParseFunction>ParseUInt</ParseFunction>
    </DeviceDictionaryRWItem>
    <DeviceDictionaryRWItem>
      <Bits>16</Bits>
      <Use>false</Use>
      <Name>Параметр 12</Name>
      <ShowFunction>ShowUInt</ShowFunction>
      <ParseFunction>ParseUInt</ParseFunction>
    </DeviceDictionaryRWItem>
    <DeviceDictionaryRWItem>
      <Bits>16</Bits>
      <Use>false</Use>
      <Name>Параметр 13</Name>
      <ShowFunction>ShowUInt</ShowFunction>
      <ParseFunction>ParseUInt</ParseFunction>
    </DeviceDictionaryRWItem>
    <DeviceDictionaryRWItem>
      <Bits>16</Bits>
      <Use>false</Use>
      <Name>Параметр 14</Name>
      <ShowFunction>ShowUInt</ShowFunction>
      <ParseFunction>ParseUInt</ParseFunction>
    </DeviceDictionaryRWItem>
    <DeviceDictionaryRWItem>
      <Bits>16</Bits>
      <Use>false</Use>
      <Name>Параметр 15</Name>
      <ShowFunction>ShowUInt</ShowFunction>
      <ParseFunction>ParseUInt</ParseFunction>
    </DeviceDictionaryRWItem>
    <DeviceDictionaryRWItem>
      <Bits>16</Bits>
      <Use>false</Use>
      <Name>Параметр 16</Name>
      <ShowFunction>ShowUInt</ShowFunction>
      <ParseFunction>ParseUInt</ParseFunction>
    </DeviceDictionaryRWItem>
    <DeviceDictionaryRWItem>
      <Bits>16</Bits>
      <Use>false</Use>
      <Name>Параметр 17</Name>
      <ShowFunction>ShowUInt</ShowFunction>
      <ParseFunction>ParseUInt</ParseFunction>
    </DeviceDictionaryRWItem>
    <DeviceDictionaryRWItem>
      <Bits>16</Bits>
      <Use>false</Use>
      <Name>Параметр 18</Name>
      <ShowFunction>ShowUInt</ShowFunction>
      <ParseFunction>ParseUInt</ParseFunction>
    </DeviceDictionaryRWItem>
    <DeviceDictionaryRWItem>
      <Bits>16</Bits>
      <Use>false</Use>
      <Name>Параметр 19</Name>
      <ShowFunction>ShowUInt</ShowFunction>
      <ParseFunction>ParseUInt</ParseFunction>
    </DeviceDictionaryRWItem>
    <DeviceDictionaryRWItem>
      <Bits>16</Bits>
      <Use>false</Use>
      <Name>Параметр 20</Name>
      <ShowFunction>ShowUInt</ShowFunction>
      <ParseFunction>ParseUInt</ParseFunction>
    </DeviceDictionaryRWItem>
    <DeviceDictionaryRWItem>
      <Bits>16</Bits>
      <Use>false</Use>
      <Name>Параметр 21</Name>
      <ShowFunction>ShowUInt</ShowFunction>
      <ParseFunction>ParseUInt</ParseFunction>
    </DeviceDictionaryRWItem>
    <DeviceDictionaryRWItem>
      <Bits>16</Bits>
      <Use>false</Use>
      <Name>Параметр 22</Name>
      <ShowFunction>ShowUInt</ShowFunction>
      <ParseFunction>ParseUInt</ParseFunction>
    </DeviceDictionaryRWItem>
    <DeviceDictionaryRWItem>
      <Bits>16</Bits>
      <Use>false</Use>
      <Name>Параметр 23</Name>
      <ShowFunction>ShowUInt</ShowFunction>
      <ParseFunction>ParseUInt</ParseFunction>
    </DeviceDictionaryRWItem>
    <DeviceDictionaryRWItem>
      <Bits>16</Bits>
      <Use>false</Use>
      <Name>Параметр 24</Name>
      <ShowFunction>ShowUInt</ShowFunction>
      <ParseFunction>ParseUInt</ParseFunction>
    </DeviceDictionaryRWItem>
    <DeviceDictionaryRWItem>
      <Bits>16</Bits>
      <Use>false</Use>
      <Name>Параметр 25</Name>
      <ShowFunction>ShowUInt</ShowFunction>
      <ParseFunction>ParseUInt</ParseFunction>
    </DeviceDictionaryRWItem>
    <DeviceDictionaryRWItem>
      <Bits>16</Bits>
      <Use>false</Use>
      <Name>Параметр 26</Name>
      <ShowFunction>ShowUInt</ShowFunction>
      <ParseFunction>ParseUInt</ParseFunction>
    </DeviceDictionaryRWItem>
    <DeviceDictionaryRWItem>
      <Bits>16</Bits>
      <Use>false</Use>
      <Name>Параметр 27</Name>
      <ShowFunction>ShowUInt</ShowFunction>
      <ParseFunction>ParseUInt</ParseFunction>
    </DeviceDictionaryRWItem>
    <DeviceDictionaryRWItem>
      <Bits>16</Bits>
      <Use>false</Use>
      <Name>Параметр 28</Name>
      <ShowFunction>ShowUInt</ShowFunction>
      <ParseFunction>ParseUInt</ParseFunction>
    </DeviceDictionaryRWItem>
    <DeviceDictionaryRWItem>
      <Bits>16</Bits>
      <Use>false</Use>
      <Name>Параметр 29</Name>
      <ShowFunction>ShowUInt</ShowFunction>
      <ParseFunction>ParseUInt</ParseFunction>
    </DeviceDictionaryRWItem>
    <DeviceDictionaryRWItem>
      <Bits>16</Bits>
      <Use>false</Use>
      <Name>Параметр 30</Name>
      <ShowFunction>ShowUInt</ShowFunction>
      <ParseFunction>ParseUInt</ParseFunction>
    </DeviceDictionaryRWItem>
    <DeviceDictionaryRWItem>
      <Bits>16</Bits>
      <Use>false</Use>
      <Name>Параметр 31</Name>
      <ShowFunction>ShowUInt</ShowFunction>
      <ParseFunction>ParseUInt</ParseFunction>
    </DeviceDictionaryRWItem>
    <DeviceDictionaryRWItem>
      <Bits>16</Bits>
      <Use>false</Use>
      <Name>Параметр 32</Name>
      <ShowFunction>ShowUInt</ShowFunction>
      <ParseFunction>ParseUInt</ParseFunction>
    </DeviceDictionaryRWItem>
    <DeviceDictionaryRWItem>
      <Bits>16</Bits>
      <Use>false</Use>
      <Name>Параметр 33</Name>
      <ShowFunction>ShowUInt</ShowFunction>
      <ParseFunction>ParseUInt</ParseFunction>
    </DeviceDictionaryRWItem>
    <DeviceDictionaryRWItem>
      <Bits>16</Bits>
      <Use>false</Use>
      <Name>Параметр 34</Name>
      <ShowFunction>ShowUInt</ShowFunction>
      <ParseFunction>ParseUInt</ParseFunction>
    </DeviceDictionaryRWItem>
    <DeviceDictionaryRWItem>
      <Bits>16</Bits>
      <Use>false</Use>
      <Name>Параметр 35</Name>
      <ShowFunction>ShowUInt</ShowFunction>
      <ParseFunction>ParseUInt</ParseFunction>
    </DeviceDictionaryRWItem>
    <DeviceDictionaryRWItem>
      <Bits>16</Bits>
      <Use>false</Use>
      <Name>Параметр 36</Name>
      <ShowFunction>ShowUInt</ShowFunction>
      <ParseFunction>ParseUInt</ParseFunction>
    </DeviceDictionaryRWItem>
    <DeviceDictionaryRWItem>
      <Bits>16</Bits>
      <Use>false</Use>
      <Name>Параметр 37</Name>
      <ShowFunction>ShowUInt</ShowFunction>
      <ParseFunction>ParseUInt</ParseFunction>
    </DeviceDictionaryRWItem>
    <DeviceDictionaryRWItem>
      <Bits>16</Bits>
      <Use>false</Use>
      <Name>Параметр 38</Name>
      <ShowFunction>ShowUInt</ShowFunction>
      <ParseFunction>ParseUInt</ParseFunction>
    </DeviceDictionaryRWItem>
    <DeviceDictionaryRWItem>
      <Bits>16</Bits>
      <Use>false</Use>
      <Name>Параметр 39</Name>
      <ShowFunction>ShowUInt</ShowFunction>
      <ParseFunction>ParseUInt</ParseFunction>
    </DeviceDictionaryRWItem>
    <DeviceDictionaryRWItem>
      <Bits>16</Bits>
      <Use>false</Use>
      <Name>Параметр 40</Name>
      <ShowFunction>ShowUInt</ShowFunction>
      <ParseFunction>ParseUInt</ParseFunction>
    </DeviceDictionaryRWItem>
    <DeviceDictionaryRWItem>
      <Bits>16</Bits>
      <Use>false</Use>
      <Name>Параметр 41</Name>
      <ShowFunction>ShowUInt</ShowFunction>
      <ParseFunction>ParseUInt</ParseFunction>
    </DeviceDictionaryRWItem>
    <DeviceDictionaryRWItem>
      <Bits>16</Bits>
      <Use>false</Use>
      <Name>Параметр 42</Name>
      <ShowFunction>ShowUInt</ShowFunction>
      <ParseFunction>ParseUInt</ParseFunction>
    </DeviceDictionaryRWItem>
    <DeviceDictionaryRWItem>
      <Bits>16</Bits>
      <Use>false</Use>
      <Name>Параметр 43</Name>
      <ShowFunction>ShowUInt</ShowFunction>
      <ParseFunction>ParseUInt</ParseFunction>
    </DeviceDictionaryRWItem>
    <DeviceDictionaryRWItem>
      <Bits>16</Bits>
      <Use>false</Use>
      <Name>Параметр 44</Name>
      <ShowFunction>ShowUInt</ShowFunction>
      <ParseFunction>ParseUInt</ParseFunction>
    </DeviceDictionaryRWItem>
    <DeviceDictionaryRWItem>
      <Bits>16</Bits>
      <Use>false</Use>
      <Name>Параметр 45</Name>
      <ShowFunction>ShowUInt</ShowFunction>
      <ParseFunction>ParseUInt</ParseFunction>
    </DeviceDictionaryRWItem>
    <DeviceDictionaryRWItem>
      <Bits>16</Bits>
      <Use>false</Use>
      <Name>Параметр 46</Name>
      <ShowFunction>ShowUInt</ShowFunction>
      <ParseFunction>ParseUInt</ParseFunction>
    </DeviceDictionaryRWItem>
    <DeviceDictionaryRWItem>
      <Bits>16</Bits>
      <Use>false</Use>
      <Name>Параметр 47</Name>
      <ShowFunction>ShowUInt</ShowFunction>
      <ParseFunction>ParseUInt</ParseFunction>
    </DeviceDictionaryRWItem>
    <DeviceDictionaryRWItem>
      <Bits>16</Bits>
      <Use>false</Use>
      <Name>Параметр 48</Name>
      <ShowFunction>ShowUInt</ShowFunction>
      <ParseFunction>ParseUInt</ParseFunction>
    </DeviceDictionaryRWItem>
    <DeviceDictionaryRWItem>
      <Bits>16</Bits>
      <Use>false</Use>
      <Name>Параметр 49</Name>
      <ShowFunction>ShowUInt</ShowFunction>
      <ParseFunction>ParseUInt</ParseFunction>
    </DeviceDictionaryRWItem>
    <DeviceDictionaryRWItem>
      <Bits>16</Bits>
      <Use>false</Use>
      <Name>Параметр 50</Name>
      <ShowFunction>ShowUInt</ShowFunction>
      <ParseFunction>ParseUInt</ParseFunction>
    </DeviceDictionaryRWItem>
    <DeviceDictionaryRWItem>
      <Bits>16</Bits>
      <Use>false</Use>
      <Name>Параметр 51</Name>
      <ShowFunction>ShowUInt</ShowFunction>
      <ParseFunction>ParseUInt</ParseFunction>
    </DeviceDictionaryRWItem>
    <DeviceDictionaryRWItem>
      <Bits>16</Bits>
      <Use>false</Use>
      <Name>Параметр 52</Name>
      <ShowFunction>ShowUInt</ShowFunction>
      <ParseFunction>ParseUInt</ParseFunction>
    </DeviceDictionaryRWItem>
    <DeviceDictionaryRWItem>
      <Bits>16</Bits>
      <Use>false</Use>
      <Name>Параметр 53</Name>
      <ShowFunction>ShowUInt</ShowFunction>
      <ParseFunction>ParseUInt</ParseFunction>
    </DeviceDictionaryRWItem>
    <DeviceDictionaryRWItem>
      <Bits>16</Bits>
      <Use>false</Use>
      <Name>Параметр 54</Name>
      <ShowFunction>ShowUInt</ShowFunction>
      <ParseFunction>ParseUInt</ParseFunction>
    </DeviceDictionaryRWItem>
    <DeviceDictionaryRWItem>
      <Bits>16</Bits>
      <Use>false</Use>
      <Name>Параметр 55</Name>
      <ShowFunction>ShowUInt</ShowFunction>
      <ParseFunction>ParseUInt</ParseFunction>
    </DeviceDictionaryRWItem>
    <DeviceDictionaryRWItem>
      <Bits>16</Bits>
      <Use>false</Use>
      <Name>Параметр 56</Name>
      <ShowFunction>ShowUInt</ShowFunction>
      <ParseFunction>ParseUInt</ParseFunction>
    </DeviceDictionaryRWItem>
    <DeviceDictionaryRWItem>
      <Bits>16</Bits>
      <Use>false</Use>
      <Name>Параметр 57</Name>
      <ShowFunction>ShowUInt</ShowFunction>
      <ParseFunction>ParseUInt</ParseFunction>
    </DeviceDictionaryRWItem>
    <DeviceDictionaryRWItem>
      <Bits>16</Bits>
      <Use>false</Use>
      <Name>Параметр 58</Name>
      <ShowFunction>ShowUInt</ShowFunction>
      <ParseFunction>ParseUInt</ParseFunction>
    </DeviceDictionaryRWItem>
    <DeviceDictionaryRWItem>
      <Bits>16</Bits>
      <Use>false</Use>
      <Name>Параметр 59</Name>
      <ShowFunction>ShowUInt</ShowFunction>
      <ParseFunction>ParseUInt</ParseFunction>
    </DeviceDictionaryRWItem>
    <DeviceDictionaryRWItem>
      <Bits>16</Bits>
      <Use>false</Use>
      <Name>Параметр 60</Name>
      <ShowFunction>ShowUInt</ShowFunction>
      <ParseFunction>ParseUInt</ParseFunction>
    </DeviceDictionaryRWItem>
    <DeviceDictionaryRWItem>
      <Bits>16</Bits>
      <Use>false</Use>
      <Name>Параметр 61</Name>
      <ShowFunction>ShowUInt</ShowFunction>
      <ParseFunction>ParseUInt</ParseFunction>
    </DeviceDictionaryRWItem>
    <DeviceDictionaryRWItem>
      <Bits>16</Bits>
      <Use>false</Use>
      <Name>Параметр 62</Name>
      <ShowFunction>ShowUInt</ShowFunction>
      <ParseFunction>ParseUInt</ParseFunction>
    </DeviceDictionaryRWItem>
    <DeviceDictionaryRWItem>
      <Bits>16</Bits>
      <Use>false</Use>
      <Name>Параметр 63</Name>
      <ShowFunction>ShowUInt</ShowFunction>
      <ParseFunction>ParseUInt</ParseFunction>
    </DeviceDictionaryRWItem>
    <DeviceDictionaryRWItem>
      <Bits>16</Bits>
      <Use>false</Use>
      <Name>Параметр 64</Name>
      <ShowFunction>ShowUInt</ShowFunction>
      <ParseFunction>ParseUInt</ParseFunction>
    </DeviceDictionaryRWItem>
    <DeviceDictionaryRWItem>
      <Bits>16</Bits>
      <Use>false</Use>
      <Name>Параметр 65</Name>
      <ShowFunction>ShowUInt</ShowFunction>
      <ParseFunction>ParseUInt</ParseFunction>
    </DeviceDictionaryRWItem>
    <DeviceDictionaryRWItem>
      <Bits>16</Bits>
      <Use>false</Use>
      <Name>Параметр 66</Name>
      <ShowFunction>ShowUInt</ShowFunction>
      <ParseFunction>ParseUInt</ParseFunction>
    </DeviceDictionaryRWItem>
    <DeviceDictionaryRWItem>
      <Bits>16</Bits>
      <Use>false</Use>
      <Name>Параметр 67</Name>
      <ShowFunction>ShowUInt</ShowFunction>
      <ParseFunction>ParseUInt</ParseFunction>
    </DeviceDictionaryRWItem>
    <DeviceDictionaryRWItem>
      <Bits>16</Bits>
      <Use>false</Use>
      <Name>Параметр 68</Name>
      <ShowFunction>ShowUInt</ShowFunction>
      <ParseFunction>ParseUInt</ParseFunction>
    </DeviceDictionaryRWItem>
    <DeviceDictionaryRWItem>
      <Bits>16</Bits>
      <Use>false</Use>
      <Name>Параметр 69</Name>
      <ShowFunction>ShowUInt</ShowFunction>
      <ParseFunction>ParseUInt</ParseFunction>
    </DeviceDictionaryRWItem>
    <DeviceDictionaryRWItem>
      <Bits>16</Bits>
      <Use>false</Use>
      <Name>Параметр 70</Name>
      <ShowFunction>ShowUInt</ShowFunction>
      <ParseFunction>ParseUInt</ParseFunction>
    </DeviceDictionaryRWItem>
    <DeviceDictionaryRWItem>
      <Bits>16</Bits>
      <Use>false</Use>
      <Name>Параметр 71</Name>
      <ShowFunction>ShowUInt</ShowFunction>
      <ParseFunction>ParseUInt</ParseFunction>
    </DeviceDictionaryRWItem>
    <DeviceDictionaryRWItem>
      <Bits>16</Bits>
      <Use>false</Use>
      <Name>Параметр 72</Name>
      <ShowFunction>ShowUInt</ShowFunction>
      <ParseFunction>ParseUInt</ParseFunction>
    </DeviceDictionaryRWItem>
    <DeviceDictionaryRWItem>
      <Bits>16</Bits>
      <Use>false</Use>
      <Name>Параметр 73</Name>
      <ShowFunction>ShowUInt</ShowFunction>
      <ParseFunction>ParseUInt</ParseFunction>
    </DeviceDictionaryRWItem>
    <DeviceDictionaryRWItem>
      <Bits>16</Bits>
      <Use>false</Use>
      <Name>Параметр 74</Name>
      <ShowFunction>ShowUInt</ShowFunction>
      <ParseFunction>ParseUInt</ParseFunction>
    </DeviceDictionaryRWItem>
    <DeviceDictionaryRWItem>
      <Bits>16</Bits>
      <Use>false</Use>
      <Name>Параметр 75</Name>
      <ShowFunction>ShowUInt</ShowFunction>
      <ParseFunction>ParseUInt</ParseFunction>
    </DeviceDictionaryRWItem>
    <DeviceDictionaryRWItem>
      <Bits>16</Bits>
      <Use>false</Use>
      <Name>Параметр 76</Name>
      <ShowFunction>ShowUInt</ShowFunction>
      <ParseFunction>ParseUInt</ParseFunction>
    </DeviceDictionaryRWItem>
    <DeviceDictionaryRWItem>
      <Bits>16</Bits>
      <Use>false</Use>
      <Name>Параметр 77</Name>
      <ShowFunction>ShowUInt</ShowFunction>
      <ParseFunction>ParseUInt</ParseFunction>
    </DeviceDictionaryRWItem>
    <DeviceDictionaryRWItem>
      <Bits>16</Bits>
      <Use>false</Use>
      <Name>Параметр 78</Name>
      <ShowFunction>ShowUInt</ShowFunction>
      <ParseFunction>ParseUInt</ParseFunction>
    </DeviceDictionaryRWItem>
    <DeviceDictionaryRWItem>
      <Bits>16</Bits>
      <Use>false</Use>
      <Name>Параметр 79</Name>
      <ShowFunction>ShowUInt</ShowFunction>
      <ParseFunction>ParseUInt</ParseFunction>
    </DeviceDictionaryRWItem>
    <DeviceDictionaryRWItem>
      <Bits>16</Bits>
      <Use>false</Use>
      <Name>Параметр 80</Name>
      <ShowFunction>ShowUInt</ShowFunction>
      <ParseFunction>ParseUInt</ParseFunction>
    </DeviceDictionaryRWItem>
    <DeviceDictionaryRWItem>
      <Bits>16</Bits>
      <Use>false</Use>
      <Name>Параметр 81</Name>
      <ShowFunction>ShowUInt</ShowFunction>
      <ParseFunction>ParseUInt</ParseFunction>
    </DeviceDictionaryRWItem>
    <DeviceDictionaryRWItem>
      <Bits>16</Bits>
      <Use>false</Use>
      <Name>Параметр 82</Name>
      <ShowFunction>ShowUInt</ShowFunction>
      <ParseFunction>ParseUInt</ParseFunction>
    </DeviceDictionaryRWItem>
    <DeviceDictionaryRWItem>
      <Bits>16</Bits>
      <Use>false</Use>
      <Name>Параметр 83</Name>
      <ShowFunction>ShowUInt</ShowFunction>
      <ParseFunction>ParseUInt</ParseFunction>
    </DeviceDictionaryRWItem>
    <DeviceDictionaryRWItem>
      <Bits>16</Bits>
      <Use>false</Use>
      <Name>Параметр 84</Name>
      <ShowFunction>ShowUInt</ShowFunction>
      <ParseFunction>ParseUInt</ParseFunction>
    </DeviceDictionaryRWItem>
    <DeviceDictionaryRWItem>
      <Bits>16</Bits>
      <Use>false</Use>
      <Name>Параметр 85</Name>
      <ShowFunction>ShowUInt</ShowFunction>
      <ParseFunction>ParseUInt</ParseFunction>
    </DeviceDictionaryRWItem>
    <DeviceDictionaryRWItem>
      <Bits>16</Bits>
      <Use>false</Use>
      <Name>Параметр 86</Name>
      <ShowFunction>ShowUInt</ShowFunction>
      <ParseFunction>ParseUInt</ParseFunction>
    </DeviceDictionaryRWItem>
    <DeviceDictionaryRWItem>
      <Bits>16</Bits>
      <Use>false</Use>
      <Name>Параметр 87</Name>
      <ShowFunction>ShowUInt</ShowFunction>
      <ParseFunction>ParseUInt</ParseFunction>
    </DeviceDictionaryRWItem>
    <DeviceDictionaryRWItem>
      <Bits>16</Bits>
      <Use>false</Use>
      <Name>Параметр 88</Name>
      <ShowFunction>ShowUInt</ShowFunction>
      <ParseFunction>ParseUInt</ParseFunction>
    </DeviceDictionaryRWItem>
    <DeviceDictionaryRWItem>
      <Bits>16</Bits>
      <Use>false</Use>
      <Name>Параметр 89</Name>
      <ShowFunction>ShowUInt</ShowFunction>
      <ParseFunction>ParseUInt</ParseFunction>
    </DeviceDictionaryRWItem>
    <DeviceDictionaryRWItem>
      <Bits>16</Bits>
      <Use>false</Use>
      <Name>Параметр 90</Name>
      <ShowFunction>ShowUInt</ShowFunction>
      <ParseFunction>ParseUInt</ParseFunction>
    </DeviceDictionaryRWItem>
    <DeviceDictionaryRWItem>
      <Bits>16</Bits>
      <Use>false</Use>
      <Name>Параметр 91</Name>
      <ShowFunction>ShowUInt</ShowFunction>
      <ParseFunction>ParseUInt</ParseFunction>
    </DeviceDictionaryRWItem>
    <DeviceDictionaryRWItem>
      <Bits>16</Bits>
      <Use>false</Use>
      <Name>Параметр 92</Name>
      <ShowFunction>ShowUInt</ShowFunction>
      <ParseFunction>ParseUInt</ParseFunction>
    </DeviceDictionaryRWItem>
    <DeviceDictionaryRWItem>
      <Bits>16</Bits>
      <Use>false</Use>
      <Name>Параметр 93</Name>
      <ShowFunction>ShowUInt</ShowFunction>
      <ParseFunction>ParseUInt</ParseFunction>
    </DeviceDictionaryRWItem>
    <DeviceDictionaryRWItem>
      <Bits>16</Bits>
      <Use>false</Use>
      <Name>Параметр 94</Name>
      <ShowFunction>ShowUInt</ShowFunction>
      <ParseFunction>ParseUInt</ParseFunction>
    </DeviceDictionaryRWItem>
    <DeviceDictionaryRWItem>
      <Bits>16</Bits>
      <Use>false</Use>
      <Name>Параметр 95</Name>
      <ShowFunction>ShowUInt</ShowFunction>
      <ParseFunction>ParseUInt</ParseFunction>
    </DeviceDictionaryRWItem>
    <DeviceDictionaryRWItem>
      <Bits>16</Bits>
      <Use>false</Use>
      <Name>Параметр 96</Name>
      <ShowFunction>ShowUInt</ShowFunction>
      <ParseFunction>ParseUInt</ParseFunction>
    </DeviceDictionaryRWItem>
    <DeviceDictionaryRWItem>
      <Bits>16</Bits>
      <Use>false</Use>
      <Name>Параметр 97</Name>
      <ShowFunction>ShowUInt</ShowFunction>
      <ParseFunction>ParseUInt</ParseFunction>
    </DeviceDictionaryRWItem>
    <DeviceDictionaryRWItem>
      <Bits>16</Bits>
      <Use>false</Use>
      <Name>Параметр 98</Name>
      <ShowFunction>ShowUInt</ShowFunction>
      <ParseFunction>ParseUInt</ParseFunction>
    </DeviceDictionaryRWItem>
    <DeviceDictionaryRWItem>
      <Bits>16</Bits>
      <Use>false</Use>
      <Name>Параметр 99</Name>
      <ShowFunction>ShowUInt</ShowFunction>
      <ParseFunction>ParseUInt</ParseFunction>
    </DeviceDictionaryRWItem>
    <DeviceDictionaryRWItem>
      <Bits>16</Bits>
      <Use>false</Use>
      <Name>Параметр 100</Name>
      <ShowFunction>ShowUInt</ShowFunction>
      <ParseFunction>ParseUInt</ParseFunction>
    </DeviceDictionaryRWItem>
    <DeviceDictionaryRWItem>
      <Bits>16</Bits>
      <Use>false</Use>
      <Name>Параметр 101</Name>
      <ShowFunction>ShowUInt</ShowFunction>
      <ParseFunction>ParseUInt</ParseFunction>
    </DeviceDictionaryRWItem>
    <DeviceDictionaryRWItem>
      <Bits>16</Bits>
      <Use>false</Use>
      <Name>Параметр 102</Name>
      <ShowFunction>ShowUInt</ShowFunction>
      <ParseFunction>ParseUInt</ParseFunction>
    </DeviceDictionaryRWItem>
    <DeviceDictionaryRWItem>
      <Bits>16</Bits>
      <Use>false</Use>
      <Name>Параметр 103</Name>
      <ShowFunction>ShowUInt</ShowFunction>
      <ParseFunction>ParseUInt</ParseFunction>
    </DeviceDictionaryRWItem>
    <DeviceDictionaryRWItem>
      <Bits>16</Bits>
      <Use>false</Use>
      <Name>Параметр 104</Name>
      <ShowFunction>ShowUInt</ShowFunction>
      <ParseFunction>ParseUInt</ParseFunction>
    </DeviceDictionaryRWItem>
    <DeviceDictionaryRWItem>
      <Bits>16</Bits>
      <Use>false</Use>
      <Name>Параметр 105</Name>
      <ShowFunction>ShowUInt</ShowFunction>
      <ParseFunction>ParseUInt</ParseFunction>
    </DeviceDictionaryRWItem>
    <DeviceDictionaryRWItem>
      <Bits>16</Bits>
      <Use>false</Use>
      <Name>Параметр 106</Name>
      <ShowFunction>ShowUInt</ShowFunction>
      <ParseFunction>ParseUInt</ParseFunction>
    </DeviceDictionaryRWItem>
    <DeviceDictionaryRWItem>
      <Bits>16</Bits>
      <Use>false</Use>
      <Name>Параметр 107</Name>
      <ShowFunction>ShowUInt</ShowFunction>
      <ParseFunction>ParseUInt</ParseFunction>
    </DeviceDictionaryRWItem>
    <DeviceDictionaryRWItem>
      <Bits>16</Bits>
      <Use>false</Use>
      <Name>Параметр 108</Name>
      <ShowFunction>ShowUInt</ShowFunction>
      <ParseFunction>ParseUInt</ParseFunction>
    </DeviceDictionaryRWItem>
    <DeviceDictionaryRWItem>
      <Bits>16</Bits>
      <Use>false</Use>
      <Name>Параметр 109</Name>
      <ShowFunction>ShowUInt</ShowFunction>
      <ParseFunction>ParseUInt</ParseFunction>
    </DeviceDictionaryRWItem>
    <DeviceDictionaryRWItem>
      <Bits>16</Bits>
      <Use>false</Use>
      <Name>Параметр 110</Name>
      <ShowFunction>ShowUInt</ShowFunction>
      <ParseFunction>ParseUInt</ParseFunction>
    </DeviceDictionaryRWItem>
    <DeviceDictionaryRWItem>
      <Bits>16</Bits>
      <Use>false</Use>
      <Name>Параметр 111</Name>
      <ShowFunction>ShowUInt</ShowFunction>
      <ParseFunction>ParseUInt</ParseFunction>
    </DeviceDictionaryRWItem>
    <DeviceDictionaryRWItem>
      <Bits>16</Bits>
      <Use>false</Use>
      <Name>Параметр 112</Name>
      <ShowFunction>ShowUInt</ShowFunction>
      <ParseFunction>ParseUInt</ParseFunction>
    </DeviceDictionaryRWItem>
    <DeviceDictionaryRWItem>
      <Bits>16</Bits>
      <Use>false</Use>
      <Name>Параметр 113</Name>
      <ShowFunction>ShowUInt</ShowFunction>
      <ParseFunction>ParseUInt</ParseFunction>
    </DeviceDictionaryRWItem>
    <DeviceDictionaryRWItem>
      <Bits>16</Bits>
      <Use>false</Use>
      <Name>Параметр 114</Name>
      <ShowFunction>ShowUInt</ShowFunction>
      <ParseFunction>ParseUInt</ParseFunction>
    </DeviceDictionaryRWItem>
    <DeviceDictionaryRWItem>
      <Bits>16</Bits>
      <Use>false</Use>
      <Name>Параметр 115</Name>
      <ShowFunction>ShowUInt</ShowFunction>
      <ParseFunction>ParseUInt</ParseFunction>
    </DeviceDictionaryRWItem>
    <DeviceDictionaryRWItem>
      <Bits>16</Bits>
      <Use>false</Use>
      <Name>Параметр 116</Name>
      <ShowFunction>ShowUInt</ShowFunction>
      <ParseFunction>ParseUInt</ParseFunction>
    </DeviceDictionaryRWItem>
    <DeviceDictionaryRWItem>
      <Bits>16</Bits>
      <Use>false</Use>
      <Name>Параметр 117</Name>
      <ShowFunction>ShowUInt</ShowFunction>
      <ParseFunction>ParseUInt</ParseFunction>
    </DeviceDictionaryRWItem>
    <DeviceDictionaryRWItem>
      <Bits>16</Bits>
      <Use>false</Use>
      <Name>Параметр 118</Name>
      <ShowFunction>ShowUInt</ShowFunction>
      <ParseFunction>ParseUInt</ParseFunction>
    </DeviceDictionaryRWItem>
    <DeviceDictionaryRWItem>
      <Bits>16</Bits>
      <Use>false</Use>
      <Name>Параметр 119</Name>
      <ShowFunction>ShowUInt</ShowFunction>
      <ParseFunction>ParseUInt</ParseFunction>
    </DeviceDictionaryRWItem>
    <DeviceDictionaryRWItem>
      <Bits>16</Bits>
      <Use>false</Use>
      <Name>Параметр 120</Name>
      <ShowFunction>ShowUInt</ShowFunction>
      <ParseFunction>ParseUInt</ParseFunction>
    </DeviceDictionaryRWItem>
    <DeviceDictionaryRWItem>
      <Bits>16</Bits>
      <Use>false</Use>
      <Name>Параметр 121</Name>
      <ShowFunction>ShowUInt</ShowFunction>
      <ParseFunction>ParseUInt</ParseFunction>
    </DeviceDictionaryRWItem>
    <DeviceDictionaryRWItem>
      <Bits>16</Bits>
      <Use>false</Use>
      <Name>Параметр 122</Name>
      <ShowFunction>ShowUInt</ShowFunction>
      <ParseFunction>ParseUInt</ParseFunction>
    </DeviceDictionaryRWItem>
    <DeviceDictionaryRWItem>
      <Bits>16</Bits>
      <Use>false</Use>
      <Name>Параметр 123</Name>
      <ShowFunction>ShowUInt</ShowFunction>
      <ParseFunction>ParseUInt</ParseFunction>
    </DeviceDictionaryRWItem>
    <DeviceDictionaryRWItem>
      <Bits>16</Bits>
      <Use>false</Use>
      <Name>Параметр 124</Name>
      <ShowFunction>ShowUInt</ShowFunction>
      <ParseFunction>ParseUInt</ParseFunction>
    </DeviceDictionaryRWItem>
    <DeviceDictionaryRWItem>
      <Bits>16</Bits>
      <Use>false</Use>
      <Name>Параметр</Name>
      <ShowFunction>ShowUInt</ShowFunction>
      <ParseFunction>ParseUInt</ParseFunction>
    </DeviceDictionaryRWItem>
    <DeviceDictionaryRWItem>
      <Bits>16</Bits>
      <Use>false</Use>
      <Name>Параметр</Name>
      <ShowFunction>ShowUInt</ShowFunction>
      <ParseFunction>ParseUInt</ParseFunction>
    </DeviceDictionaryRWItem>
    <DeviceDictionaryRWItem>
      <Bits>16</Bits>
      <Use>false</Use>
      <Name>Параметр</Name>
      <ShowFunction>ShowUInt</ShowFunction>
      <ParseFunction>ParseUInt</ParseFunction>
    </DeviceDictionaryRWItem>
    <DeviceDictionaryRWItem>
      <Bits>16</Bits>
      <Use>false</Use>
      <Name>Параметр</Name>
      <ShowFunction>ShowUInt</ShowFunction>
      <ParseFunction>ParseUInt</ParseFunction>
    </DeviceDictionaryRWItem>
    <DeviceDictionaryRWItem>
      <Bits>16</Bits>
      <Use>false</Use>
      <Name>Параметр</Name>
      <ShowFunction>ShowUInt</ShowFunction>
      <ParseFunction>ParseUInt</ParseFunction>
    </DeviceDictionaryRWItem>
    <DeviceDictionaryRWItem>
      <Bits>16</Bits>
      <Use>false</Use>
      <Name>Параметр</Name>
      <ShowFunction>ShowUInt</ShowFunction>
      <ParseFunction>ParseUInt</ParseFunction>
    </DeviceDictionaryRWItem>
    <DeviceDictionaryRWItem>
      <Bits>16</Bits>
      <Use>false</Use>
      <Name>Параметр</Name>
      <ShowFunction>ShowUInt</ShowFunction>
      <ParseFunction>ParseUInt</ParseFunction>
    </DeviceDictionaryRWItem>
    <DeviceDictionaryRWItem>
      <Bits>16</Bits>
      <Use>false</Use>
      <Name>Параметр</Name>
      <ShowFunction>ShowUInt</ShowFunction>
      <ParseFunction>ParseUInt</ParseFunction>
    </DeviceDictionaryRWItem>
    <DeviceDictionaryRWItem>
      <Bits>16</Bits>
      <Use>false</Use>
      <Name>Параметр</Name>
      <ShowFunction>ShowUInt</ShowFunction>
      <ParseFunction>ParseUInt</ParseFunction>
    </DeviceDictionaryRWItem>
    <DeviceDictionaryRWItem>
      <Bits>16</Bits>
      <Use>false</Use>
      <Name>Параметр</Name>
      <ShowFunction>ShowUInt</ShowFunction>
      <ParseFunction>ParseUInt</ParseFunction>
    </DeviceDictionaryRWItem>
    <DeviceDictionaryRWItem>
      <Bits>16</Bits>
      <Use>false</Use>
      <Name>Параметр</Name>
      <ShowFunction>ShowUInt</ShowFunction>
      <ParseFunction>ParseUInt</ParseFunction>
    </DeviceDictionaryRWItem>
    <DeviceDictionaryRWItem>
      <Bits>16</Bits>
      <Use>false</Use>
      <Name>Параметр</Name>
      <ShowFunction>ShowUInt</ShowFunction>
      <ParseFunction>ParseUInt</ParseFunction>
    </DeviceDictionaryRWItem>
    <DeviceDictionaryRWItem>
      <Bits>16</Bits>
      <Use>false</Use>
      <Name>Параметр</Name>
      <ShowFunction>ShowUInt</ShowFunction>
      <ParseFunction>ParseUInt</ParseFunction>
    </DeviceDictionaryRWItem>
    <DeviceDictionaryRWItem>
      <Bits>16</Bits>
      <Use>false</Use>
      <Name>Параметр</Name>
      <ShowFunction>ShowUInt</ShowFunction>
      <ParseFunction>ParseUInt</ParseFunction>
    </DeviceDictionaryRWItem>
    <DeviceDictionaryRWItem>
      <Bits>16</Bits>
      <Use>false</Use>
      <Name>Параметр</Name>
      <ShowFunction>ShowUInt</ShowFunction>
      <ParseFunction>ParseUInt</ParseFunction>
    </DeviceDictionaryRWItem>
    <DeviceDictionaryRWItem>
      <Bits>16</Bits>
      <Use>false</Use>
      <Name>Параметр</Name>
      <ShowFunction>ShowUInt</ShowFunction>
      <ParseFunction>ParseUInt</ParseFunction>
    </DeviceDictionaryRWItem>
    <DeviceDictionaryRWItem>
      <Bits>16</Bits>
      <Use>false</Use>
      <Name>Параметр</Name>
      <ShowFunction>ShowUInt</ShowFunction>
      <ParseFunction>ParseUInt</ParseFunction>
    </DeviceDictionaryRWItem>
    <DeviceDictionaryRWItem>
      <Bits>16</Bits>
      <Use>false</Use>
      <Name>Параметр</Name>
      <ShowFunction>ShowUInt</ShowFunction>
      <ParseFunction>ParseUInt</ParseFunction>
    </DeviceDictionaryRWItem>
    <DeviceDictionaryRWItem>
      <Bits>16</Bits>
      <Use>false</Use>
      <Name>Параметр</Name>
      <ShowFunction>ShowUInt</ShowFunction>
      <ParseFunction>ParseUInt</ParseFunction>
    </DeviceDictionaryRWItem>
    <DeviceDictionaryRWItem>
      <Bits>16</Bits>
      <Use>false</Use>
      <Name>Параметр</Name>
      <ShowFunction>ShowUInt</ShowFunction>
      <ParseFunction>ParseUInt</ParseFunction>
    </DeviceDictionaryRWItem>
    <DeviceDictionaryRWItem>
      <Bits>16</Bits>
      <Use>false</Use>
      <Name>Параметр</Name>
      <ShowFunction>ShowUInt</ShowFunction>
      <ParseFunction>ParseUInt</ParseFunction>
    </DeviceDictionaryRWItem>
    <DeviceDictionaryRWItem>
      <Bits>16</Bits>
      <Use>false</Use>
      <Name>Параметр</Name>
      <ShowFunction>ShowUInt</ShowFunction>
      <ParseFunction>ParseUInt</ParseFunction>
    </DeviceDictionaryRWItem>
    <DeviceDictionaryRWItem>
      <Bits>16</Bits>
      <Use>false</Use>
      <Name>Параметр</Name>
      <ShowFunction>ShowUInt</ShowFunction>
      <ParseFunction>ParseUInt</ParseFunction>
    </DeviceDictionaryRWItem>
    <DeviceDictionaryRWItem>
      <Bits>16</Bits>
      <Use>false</Use>
      <Name>Параметр</Name>
      <ShowFunction>ShowUInt</ShowFunction>
      <ParseFunction>ParseUInt</ParseFunction>
    </DeviceDictionaryRWItem>
    <DeviceDictionaryRWItem>
      <Bits>16</Bits>
      <Use>false</Use>
      <Name>Параметр</Name>
      <ShowFunction>ShowUInt</ShowFunction>
      <ParseFunction>ParseUInt</ParseFunction>
    </DeviceDictionaryRWItem>
    <DeviceDictionaryRWItem>
      <Bits>16</Bits>
      <Use>false</Use>
      <Name>Параметр</Name>
      <ShowFunction>ShowUInt</ShowFunction>
      <ParseFunction>ParseUInt</ParseFunction>
    </DeviceDictionaryRWItem>
    <DeviceDictionaryRWItem>
      <Bits>16</Bits>
      <Use>false</Use>
      <Name>Параметр</Name>
      <ShowFunction>ShowUInt</ShowFunction>
      <ParseFunction>ParseUInt</ParseFunction>
    </DeviceDictionaryRWItem>
    <DeviceDictionaryRWItem>
      <Bits>16</Bits>
      <Use>false</Use>
      <Name>Параметр</Name>
      <ShowFunction>ShowUInt</ShowFunction>
      <ParseFunction>ParseUInt</ParseFunction>
    </DeviceDictionaryRWItem>
    <DeviceDictionaryRWItem>
      <Bits>16</Bits>
      <Use>false</Use>
      <Name>Параметр</Name>
      <ShowFunction>ShowUInt</ShowFunction>
      <ParseFunction>ParseUInt</ParseFunction>
    </DeviceDictionaryRWItem>
    <DeviceDictionaryRWItem>
      <Bits>16</Bits>
      <Use>false</Use>
      <Name>Параметр</Name>
      <ShowFunction>ShowUInt</ShowFunction>
      <ParseFunction>ParseUInt</ParseFunction>
    </DeviceDictionaryRWItem>
    <DeviceDictionaryRWItem>
      <Bits>16</Bits>
      <Use>false</Use>
      <Name>Параметр</Name>
      <ShowFunction>ShowUInt</ShowFunction>
      <ParseFunction>ParseUInt</ParseFunction>
    </DeviceDictionaryRWItem>
    <DeviceDictionaryRWItem>
      <Bits>16</Bits>
      <Use>false</Use>
      <Name>Параметр</Name>
      <ShowFunction>ShowUInt</ShowFunction>
      <ParseFunction>ParseUInt</ParseFunction>
    </DeviceDictionaryRWItem>
    <DeviceDictionaryRWItem>
      <Bits>16</Bits>
      <Use>false</Use>
      <Name>Параметр</Name>
      <ShowFunction>ShowUInt</ShowFunction>
      <ParseFunction>ParseUInt</ParseFunction>
    </DeviceDictionaryRWItem>
    <DeviceDictionaryRWItem>
      <Bits>16</Bits>
      <Use>false</Use>
      <Name>Параметр</Name>
      <ShowFunction>ShowUInt</ShowFunction>
      <ParseFunction>ParseUInt</ParseFunction>
    </DeviceDictionaryRWItem>
    <DeviceDictionaryRWItem>
      <Bits>16</Bits>
      <Use>false</Use>
      <Name>Параметр</Name>
      <ShowFunction>ShowUInt</ShowFunction>
      <ParseFunction>ParseUInt</ParseFunction>
    </DeviceDictionaryRWItem>
    <DeviceDictionaryRWItem>
      <Bits>16</Bits>
      <Use>false</Use>
      <Name>Параметр</Name>
      <ShowFunction>ShowUInt</ShowFunction>
      <ParseFunction>ParseUInt</ParseFunction>
    </DeviceDictionaryRWItem>
    <DeviceDictionaryRWItem>
      <Bits>16</Bits>
      <Use>false</Use>
      <Name>Параметр</Name>
      <ShowFunction>ShowUInt</ShowFunction>
      <ParseFunction>ParseUInt</ParseFunction>
    </DeviceDictionaryRWItem>
    <DeviceDictionaryRWItem>
      <Bits>16</Bits>
      <Use>false</Use>
      <Name>Параметр</Name>
      <ShowFunction>ShowUInt</ShowFunction>
      <ParseFunction>ParseUInt</ParseFunction>
    </DeviceDictionaryRWItem>
    <DeviceDictionaryRWItem>
      <Bits>16</Bits>
      <Use>false</Use>
      <Name>Параметр</Name>
      <ShowFunction>ShowUInt</ShowFunction>
      <ParseFunction>ParseUInt</ParseFunction>
    </DeviceDictionaryRWItem>
    <DeviceDictionaryRWItem>
      <Bits>16</Bits>
      <Use>false</Use>
      <Name>Параметр</Name>
      <ShowFunction>ShowUInt</ShowFunction>
      <ParseFunction>ParseUInt</ParseFunction>
    </DeviceDictionaryRWItem>
    <DeviceDictionaryRWItem>
      <Bits>16</Bits>
      <Use>false</Use>
      <Name>Параметр</Name>
      <ShowFunction>ShowUInt</ShowFunction>
      <ParseFunction>ParseUInt</ParseFunction>
    </DeviceDictionaryRWItem>
    <DeviceDictionaryRWItem>
      <Bits>16</Bits>
      <Use>false</Use>
      <Name>Параметр</Name>
      <ShowFunction>ShowUInt</ShowFunction>
      <ParseFunction>ParseUInt</ParseFunction>
    </DeviceDictionaryRWItem>
    <DeviceDictionaryRWItem>
      <Bits>16</Bits>
      <Use>false</Use>
      <Name>Параметр</Name>
      <ShowFunction>ShowUInt</ShowFunction>
      <ParseFunction>ParseUInt</ParseFunction>
    </DeviceDictionaryRWItem>
    <DeviceDictionaryRWItem>
      <Bits>16</Bits>
      <Use>false</Use>
      <Name>Параметр</Name>
      <ShowFunction>ShowUInt</ShowFunction>
      <ParseFunction>ParseUInt</ParseFunction>
    </DeviceDictionaryRWItem>
    <DeviceDictionaryRWItem>
      <Bits>16</Bits>
      <Use>false</Use>
      <Name>Параметр</Name>
      <ShowFunction>ShowUInt</ShowFunction>
      <ParseFunction>ParseUInt</ParseFunction>
    </DeviceDictionaryRWItem>
    <DeviceDictionaryRWItem>
      <Bits>16</Bits>
      <Use>false</Use>
      <Name>Параметр</Name>
      <ShowFunction>ShowUInt</ShowFunction>
      <ParseFunction>ParseUInt</ParseFunction>
    </DeviceDictionaryRWItem>
    <DeviceDictionaryRWItem>
      <Bits>16</Bits>
      <Use>false</Use>
      <Name>Параметр</Name>
      <ShowFunction>ShowUInt</ShowFunction>
      <ParseFunction>ParseUInt</ParseFunction>
    </DeviceDictionaryRWItem>
    <DeviceDictionaryRWItem>
      <Bits>16</Bits>
      <Use>false</Use>
      <Name>Параметр</Name>
      <ShowFunction>ShowUInt</ShowFunction>
      <ParseFunction>ParseUInt</ParseFunction>
    </DeviceDictionaryRWItem>
    <DeviceDictionaryRWItem>
      <Bits>16</Bits>
      <Use>false</Use>
      <Name>Параметр</Name>
      <ShowFunction>ShowUInt</ShowFunction>
      <ParseFunction>ParseUInt</ParseFunction>
    </DeviceDictionaryRWItem>
    <DeviceDictionaryRWItem>
      <Bits>16</Bits>
      <Use>false</Use>
      <Name>Параметр</Name>
      <ShowFunction>ShowUInt</ShowFunction>
      <ParseFunction>ParseUInt</ParseFunction>
    </DeviceDictionaryRWItem>
    <DeviceDictionaryRWItem>
      <Bits>16</Bits>
      <Use>false</Use>
      <Name>Параметр</Name>
      <ShowFunction>ShowUInt</ShowFunction>
      <ParseFunction>ParseUInt</ParseFunction>
    </DeviceDictionaryRWItem>
    <DeviceDictionaryRWItem>
      <Bits>16</Bits>
      <Use>false</Use>
      <Name>Параметр</Name>
      <ShowFunction>ShowUInt</ShowFunction>
      <ParseFunction>ParseUInt</ParseFunction>
    </DeviceDictionaryRWItem>
    <DeviceDictionaryRWItem>
      <Bits>16</Bits>
      <Use>false</Use>
      <Name>Параметр</Name>
      <ShowFunction>ShowUInt</ShowFunction>
      <ParseFunction>ParseUInt</ParseFunction>
    </DeviceDictionaryRWItem>
    <DeviceDictionaryRWItem>
      <Bits>16</Bits>
      <Use>false</Use>
      <Name>Параметр</Name>
      <ShowFunction>ShowUInt</ShowFunction>
      <ParseFunction>ParseUInt</ParseFunction>
    </DeviceDictionaryRWItem>
    <DeviceDictionaryRWItem>
      <Bits>16</Bits>
      <Use>false</Use>
      <Name>Параметр</Name>
      <ShowFunction>ShowUInt</ShowFunction>
      <ParseFunction>ParseUInt</ParseFunction>
    </DeviceDictionaryRWItem>
    <DeviceDictionaryRWItem>
      <Bits>16</Bits>
      <Use>false</Use>
      <Name>Параметр</Name>
      <ShowFunction>ShowUInt</ShowFunction>
      <ParseFunction>ParseUInt</ParseFunction>
    </DeviceDictionaryRWItem>
    <DeviceDictionaryRWItem>
      <Bits>16</Bits>
      <Use>false</Use>
      <Name>Параметр</Name>
      <ShowFunction>ShowUInt</ShowFunction>
      <ParseFunction>ParseUInt</ParseFunction>
    </DeviceDictionaryRWItem>
    <DeviceDictionaryRWItem>
      <Bits>16</Bits>
      <Use>false</Use>
      <Name>Параметр</Name>
      <ShowFunction>ShowUInt</ShowFunction>
      <ParseFunction>ParseUInt</ParseFunction>
    </DeviceDictionaryRWItem>
    <DeviceDictionaryRWItem>
      <Bits>16</Bits>
      <Use>false</Use>
      <Name>Параметр</Name>
      <ShowFunction>ShowUInt</ShowFunction>
      <ParseFunction>ParseUInt</ParseFunction>
    </DeviceDictionaryRWItem>
    <DeviceDictionaryRWItem>
      <Bits>16</Bits>
      <Use>false</Use>
      <Name>Параметр</Name>
      <ShowFunction>ShowUInt</ShowFunction>
      <ParseFunction>ParseUInt</ParseFunction>
    </DeviceDictionaryRWItem>
    <DeviceDictionaryRWItem>
      <Bits>16</Bits>
      <Use>false</Use>
      <Name>Параметр</Name>
      <ShowFunction>ShowUInt</ShowFunction>
      <ParseFunction>ParseUInt</ParseFunction>
    </DeviceDictionaryRWItem>
    <DeviceDictionaryRWItem>
      <Bits>16</Bits>
      <Use>false</Use>
      <Name>Параметр</Name>
      <ShowFunction>ShowUInt</ShowFunction>
      <ParseFunction>ParseUInt</ParseFunction>
    </DeviceDictionaryRWItem>
    <DeviceDictionaryRWItem>
      <Bits>16</Bits>
      <Use>false</Use>
      <Name>Параметр</Name>
      <ShowFunction>ShowUInt</ShowFunction>
      <ParseFunction>ParseUInt</ParseFunction>
    </DeviceDictionaryRWItem>
    <DeviceDictionaryRWItem>
      <Bits>16</Bits>
      <Use>false</Use>
      <Name>Параметр</Name>
      <ShowFunction>ShowUInt</ShowFunction>
      <ParseFunction>ParseUInt</ParseFunction>
    </DeviceDictionaryRWItem>
    <DeviceDictionaryRWItem>
      <Bits>16</Bits>
      <Use>false</Use>
      <Name>Параметр</Name>
      <ShowFunction>ShowUInt</ShowFunction>
      <ParseFunction>ParseUInt</ParseFunction>
    </DeviceDictionaryRWItem>
    <DeviceDictionaryRWItem>
      <Bits>16</Bits>
      <Use>false</Use>
      <Name>Параметр</Name>
      <ShowFunction>ShowUInt</ShowFunction>
      <ParseFunction>ParseUInt</ParseFunction>
    </DeviceDictionaryRWItem>
    <DeviceDictionaryRWItem>
      <Bits>16</Bits>
      <Use>false</Use>
      <Name>Параметр</Name>
      <ShowFunction>ShowUInt</ShowFunction>
      <ParseFunction>ParseUInt</ParseFunction>
    </DeviceDictionaryRWItem>
    <DeviceDictionaryRWItem>
      <Bits>16</Bits>
      <Use>false</Use>
      <Name>Параметр 192</Name>
      <ShowFunction>ShowUInt</ShowFunction>
      <ParseFunction>ParseUInt</ParseFunction>
    </DeviceDictionaryRWItem>
    <DeviceDictionaryRWItem>
      <Bits>16</Bits>
      <Use>false</Use>
      <Name>Параметр 193</Name>
      <ShowFunction>ShowUInt</ShowFunction>
      <ParseFunction>ParseUInt</ParseFunction>
    </DeviceDictionaryRWItem>
    <DeviceDictionaryRWItem>
      <Bits>16</Bits>
      <Use>false</Use>
      <Name>Параметр 194</Name>
      <ShowFunction>ShowUInt</ShowFunction>
      <ParseFunction>ParseUInt</ParseFunction>
    </DeviceDictionaryRWItem>
    <DeviceDictionaryRWItem>
      <Bits>16</Bits>
      <Use>false</Use>
      <Name>Параметр 195</Name>
      <ShowFunction>ShowUInt</ShowFunction>
      <ParseFunction>ParseUInt</ParseFunction>
    </DeviceDictionaryRWItem>
    <DeviceDictionaryRWItem>
      <Bits>16</Bits>
      <Use>false</Use>
      <Name>Параметр 196</Name>
      <ShowFunction>ShowUInt</ShowFunction>
      <ParseFunction>ParseUInt</ParseFunction>
    </DeviceDictionaryRWItem>
    <DeviceDictionaryRWItem>
      <Bits>16</Bits>
      <Use>false</Use>
      <Name>Параметр 197</Name>
      <ShowFunction>ShowUInt</ShowFunction>
      <ParseFunction>ParseUInt</ParseFunction>
    </DeviceDictionaryRWItem>
    <DeviceDictionaryRWItem>
      <Bits>16</Bits>
      <Use>false</Use>
      <Name>Параметр 198</Name>
      <ShowFunction>ShowUInt</ShowFunction>
      <ParseFunction>ParseUInt</ParseFunction>
    </DeviceDictionaryRWItem>
    <DeviceDictionaryRWItem>
      <Bits>16</Bits>
      <Use>false</Use>
      <Name>Параметр 199</Name>
      <ShowFunction>ShowUInt</ShowFunction>
      <ParseFunction>ParseUInt</ParseFunction>
    </DeviceDictionaryRWItem>
    <DeviceDictionaryRWItem>
      <Bits>16</Bits>
      <Use>false</Use>
      <Name>Параметр 200</Name>
      <ShowFunction>ShowUInt</ShowFunction>
      <ParseFunction>ParseUInt</ParseFunction>
    </DeviceDictionaryRWItem>
    <DeviceDictionaryRWItem>
      <Bits>16</Bits>
      <Use>false</Use>
      <Name>Параметр 201</Name>
      <ShowFunction>ShowUInt</ShowFunction>
      <ParseFunction>ParseUInt</ParseFunction>
    </DeviceDictionaryRWItem>
    <DeviceDictionaryRWItem>
      <Bits>16</Bits>
      <Use>false</Use>
      <Name>Параметр 202</Name>
      <ShowFunction>ShowUInt</ShowFunction>
      <ParseFunction>ParseUInt</ParseFunction>
    </DeviceDictionaryRWItem>
    <DeviceDictionaryRWItem>
      <Bits>16</Bits>
      <Use>false</Use>
      <Name>Параметр 203</Name>
      <ShowFunction>ShowUInt</ShowFunction>
      <ParseFunction>ParseUInt</ParseFunction>
    </DeviceDictionaryRWItem>
    <DeviceDictionaryRWItem>
      <Bits>16</Bits>
      <Use>false</Use>
      <Name>Параметр 204</Name>
      <ShowFunction>ShowUInt</ShowFunction>
      <ParseFunction>ParseUInt</ParseFunction>
    </DeviceDictionaryRWItem>
    <DeviceDictionaryRWItem>
      <Bits>16</Bits>
      <Use>false</Use>
      <Name>Параметр 205</Name>
      <ShowFunction>ShowUInt</ShowFunction>
      <ParseFunction>ParseUInt</ParseFunction>
    </DeviceDictionaryRWItem>
    <DeviceDictionaryRWItem>
      <Bits>16</Bits>
      <Use>false</Use>
      <Name>Параметр 206</Name>
      <ShowFunction>ShowUInt</ShowFunction>
      <ParseFunction>ParseUInt</ParseFunction>
    </DeviceDictionaryRWItem>
    <DeviceDictionaryRWItem>
      <Bits>16</Bits>
      <Use>false</Use>
      <Name>Параметр 207</Name>
      <ShowFunction>ShowUInt</ShowFunction>
      <ParseFunction>ParseUInt</ParseFunction>
    </DeviceDictionaryRWItem>
    <DeviceDictionaryRWItem>
      <Bits>16</Bits>
      <Use>false</Use>
      <Name>Параметр 208</Name>
      <ShowFunction>ShowUInt</ShowFunction>
      <ParseFunction>ParseUInt</ParseFunction>
    </DeviceDictionaryRWItem>
    <DeviceDictionaryRWItem>
      <Bits>16</Bits>
      <Use>false</Use>
      <Name>Параметр 209</Name>
      <ShowFunction>ShowUInt</ShowFunction>
      <ParseFunction>ParseUInt</ParseFunction>
    </DeviceDictionaryRWItem>
    <DeviceDictionaryRWItem>
      <Bits>16</Bits>
      <Use>false</Use>
      <Name>Параметр 210</Name>
      <ShowFunction>ShowUInt</ShowFunction>
      <ParseFunction>ParseUInt</ParseFunction>
    </DeviceDictionaryRWItem>
    <DeviceDictionaryRWItem>
      <Bits>16</Bits>
      <Use>false</Use>
      <Name>Параметр 211</Name>
      <ShowFunction>ShowUInt</ShowFunction>
      <ParseFunction>ParseUInt</ParseFunction>
    </DeviceDictionaryRWItem>
    <DeviceDictionaryRWItem>
      <Bits>16</Bits>
      <Use>false</Use>
      <Name>Параметр 212</Name>
      <ShowFunction>ShowUInt</ShowFunction>
      <ParseFunction>ParseUInt</ParseFunction>
    </DeviceDictionaryRWItem>
    <DeviceDictionaryRWItem>
      <Bits>16</Bits>
      <Use>false</Use>
      <Name>Параметр 213</Name>
      <ShowFunction>ShowUInt</ShowFunction>
      <ParseFunction>ParseUInt</ParseFunction>
    </DeviceDictionaryRWItem>
    <DeviceDictionaryRWItem>
      <Bits>16</Bits>
      <Use>false</Use>
      <Name>Параметр 214</Name>
      <ShowFunction>ShowUInt</ShowFunction>
      <ParseFunction>ParseUInt</ParseFunction>
    </DeviceDictionaryRWItem>
    <DeviceDictionaryRWItem>
      <Bits>16</Bits>
      <Use>false</Use>
      <Name>Параметр 215</Name>
      <ShowFunction>ShowUInt</ShowFunction>
      <ParseFunction>ParseUInt</ParseFunction>
    </DeviceDictionaryRWItem>
    <DeviceDictionaryRWItem>
      <Bits>16</Bits>
      <Use>false</Use>
      <Name>Параметр 216</Name>
      <ShowFunction>ShowUInt</ShowFunction>
      <ParseFunction>ParseUInt</ParseFunction>
    </DeviceDictionaryRWItem>
    <DeviceDictionaryRWItem>
      <Bits>16</Bits>
      <Use>false</Use>
      <Name>Параметр 217</Name>
      <ShowFunction>ShowUInt</ShowFunction>
      <ParseFunction>ParseUInt</ParseFunction>
    </DeviceDictionaryRWItem>
    <DeviceDictionaryRWItem>
      <Bits>16</Bits>
      <Use>false</Use>
      <Name>Параметр 218</Name>
      <ShowFunction>ShowUInt</ShowFunction>
      <ParseFunction>ParseUInt</ParseFunction>
    </DeviceDictionaryRWItem>
    <DeviceDictionaryRWItem>
      <Bits>16</Bits>
      <Use>false</Use>
      <Name>Параметр 219</Name>
      <ShowFunction>ShowUInt</ShowFunction>
      <ParseFunction>ParseUInt</ParseFunction>
    </DeviceDictionaryRWItem>
    <DeviceDictionaryRWItem>
      <Bits>16</Bits>
      <Use>false</Use>
      <Name>Параметр 220</Name>
      <ShowFunction>ShowUInt</ShowFunction>
      <ParseFunction>ParseUInt</ParseFunction>
    </DeviceDictionaryRWItem>
    <DeviceDictionaryRWItem>
      <Bits>16</Bits>
      <Use>false</Use>
      <Name>Параметр 221</Name>
      <ShowFunction>ShowUInt</ShowFunction>
      <ParseFunction>ParseUInt</ParseFunction>
    </DeviceDictionaryRWItem>
    <DeviceDictionaryRWItem>
      <Bits>16</Bits>
      <Use>false</Use>
      <Name>Параметр 222</Name>
      <ShowFunction>ShowUInt</ShowFunction>
      <ParseFunction>ParseUInt</ParseFunction>
    </DeviceDictionaryRWItem>
    <DeviceDictionaryRWItem>
      <Bits>16</Bits>
      <Use>false</Use>
      <Name>Параметр 223</Name>
      <ShowFunction>ShowUInt</ShowFunction>
      <ParseFunction>ParseUInt</ParseFunction>
    </DeviceDictionaryRWItem>
    <DeviceDictionaryRWItem>
      <Bits>16</Bits>
      <Use>false</Use>
      <Name>Параметр 224</Name>
      <ShowFunction>ShowUInt</ShowFunction>
      <ParseFunction>ParseUInt</ParseFunction>
    </DeviceDictionaryRWItem>
    <DeviceDictionaryRWItem>
      <Bits>16</Bits>
      <Use>false</Use>
      <Name>Параметр 225</Name>
      <ShowFunction>ShowUInt</ShowFunction>
      <ParseFunction>ParseUInt</ParseFunction>
    </DeviceDictionaryRWItem>
    <DeviceDictionaryRWItem>
      <Bits>16</Bits>
      <Use>false</Use>
      <Name>Параметр 226</Name>
      <ShowFunction>ShowUInt</ShowFunction>
      <ParseFunction>ParseUInt</ParseFunction>
    </DeviceDictionaryRWItem>
    <DeviceDictionaryRWItem>
      <Bits>16</Bits>
      <Use>false</Use>
      <Name>Параметр 227</Name>
      <ShowFunction>ShowUInt</ShowFunction>
      <ParseFunction>ParseUInt</ParseFunction>
    </DeviceDictionaryRWItem>
    <DeviceDictionaryRWItem>
      <Bits>16</Bits>
      <Use>false</Use>
      <Name>Параметр 228</Name>
      <ShowFunction>ShowUInt</ShowFunction>
      <ParseFunction>ParseUInt</ParseFunction>
    </DeviceDictionaryRWItem>
    <DeviceDictionaryRWItem>
      <Bits>16</Bits>
      <Use>false</Use>
      <Name>Параметр 229</Name>
      <ShowFunction>ShowUInt</ShowFunction>
      <ParseFunction>ParseUInt</ParseFunction>
    </DeviceDictionaryRWItem>
    <DeviceDictionaryRWItem>
      <Bits>16</Bits>
      <Use>false</Use>
      <Name>Параметр 230</Name>
      <ShowFunction>ShowUInt</ShowFunction>
      <ParseFunction>ParseUInt</ParseFunction>
    </DeviceDictionaryRWItem>
    <DeviceDictionaryRWItem>
      <Bits>16</Bits>
      <Use>false</Use>
      <Name>Параметр 231</Name>
      <ShowFunction>ShowUInt</ShowFunction>
      <ParseFunction>ParseUInt</ParseFunction>
    </DeviceDictionaryRWItem>
    <DeviceDictionaryRWItem>
      <Bits>16</Bits>
      <Use>false</Use>
      <Name>Параметр 232</Name>
      <ShowFunction>ShowUInt</ShowFunction>
      <ParseFunction>ParseUInt</ParseFunction>
    </DeviceDictionaryRWItem>
    <DeviceDictionaryRWItem>
      <Bits>16</Bits>
      <Use>false</Use>
      <Name>Параметр 233</Name>
      <ShowFunction>ShowUInt</ShowFunction>
      <ParseFunction>ParseUInt</ParseFunction>
    </DeviceDictionaryRWItem>
    <DeviceDictionaryRWItem>
      <Bits>16</Bits>
      <Use>false</Use>
      <Name>Параметр 234</Name>
      <ShowFunction>ShowUInt</ShowFunction>
      <ParseFunction>ParseUInt</ParseFunction>
    </DeviceDictionaryRWItem>
    <DeviceDictionaryRWItem>
      <Bits>16</Bits>
      <Use>false</Use>
      <Name>Параметр 235</Name>
      <ShowFunction>ShowUInt</ShowFunction>
      <ParseFunction>ParseUInt</ParseFunction>
    </DeviceDictionaryRWItem>
    <DeviceDictionaryRWItem>
      <Bits>16</Bits>
      <Use>false</Use>
      <Name>Параметр 236</Name>
      <ShowFunction>ShowUInt</ShowFunction>
      <ParseFunction>ParseUInt</ParseFunction>
    </DeviceDictionaryRWItem>
    <DeviceDictionaryRWItem>
      <Bits>16</Bits>
      <Use>false</Use>
      <Name>Параметр 237</Name>
      <ShowFunction>ShowUInt</ShowFunction>
      <ParseFunction>ParseUInt</ParseFunction>
    </DeviceDictionaryRWItem>
    <DeviceDictionaryRWItem>
      <Bits>16</Bits>
      <Use>false</Use>
      <Name>Параметр 238</Name>
      <ShowFunction>ShowUInt</ShowFunction>
      <ParseFunction>ParseUInt</ParseFunction>
    </DeviceDictionaryRWItem>
    <DeviceDictionaryRWItem>
      <Bits>16</Bits>
      <Use>false</Use>
      <Name>Параметр 239</Name>
      <ShowFunction>ShowUInt</ShowFunction>
      <ParseFunction>ParseUInt</ParseFunction>
    </DeviceDictionaryRWItem>
    <DeviceDictionaryRWItem>
      <Bits>16</Bits>
      <Use>false</Use>
      <Name>Параметр 240</Name>
      <ShowFunction>ShowUInt</ShowFunction>
      <ParseFunction>ParseUInt</ParseFunction>
    </DeviceDictionaryRWItem>
    <DeviceDictionaryRWItem>
      <Bits>16</Bits>
      <Use>false</Use>
      <Name>Параметр 241</Name>
      <ShowFunction>ShowUInt</ShowFunction>
      <ParseFunction>ParseUInt</ParseFunction>
    </DeviceDictionaryRWItem>
    <DeviceDictionaryRWItem>
      <Bits>16</Bits>
      <Use>false</Use>
      <Name>Параметр 242</Name>
      <ShowFunction>ShowUInt</ShowFunction>
      <ParseFunction>ParseUInt</ParseFunction>
    </DeviceDictionaryRWItem>
    <DeviceDictionaryRWItem>
      <Bits>16</Bits>
      <Use>false</Use>
      <Name>Параметр 243</Name>
      <ShowFunction>ShowUInt</ShowFunction>
      <ParseFunction>ParseUInt</ParseFunction>
    </DeviceDictionaryRWItem>
    <DeviceDictionaryRWItem>
      <Bits>16</Bits>
      <Use>false</Use>
      <Name>Параметр 244</Name>
      <ShowFunction>ShowUInt</ShowFunction>
      <ParseFunction>ParseUInt</ParseFunction>
    </DeviceDictionaryRWItem>
    <DeviceDictionaryRWItem>
      <Bits>16</Bits>
      <Use>false</Use>
      <Name>Параметр 245</Name>
      <ShowFunction>ShowUInt</ShowFunction>
      <ParseFunction>ParseUInt</ParseFunction>
    </DeviceDictionaryRWItem>
    <DeviceDictionaryRWItem>
      <Bits>16</Bits>
      <Use>false</Use>
      <Name>Параметр 246</Name>
      <ShowFunction>ShowUInt</ShowFunction>
      <ParseFunction>ParseUInt</ParseFunction>
    </DeviceDictionaryRWItem>
    <DeviceDictionaryRWItem>
      <Bits>16</Bits>
      <Use>false</Use>
      <Name>Параметр 247</Name>
      <ShowFunction>ShowUInt</ShowFunction>
      <ParseFunction>ParseUInt</ParseFunction>
    </DeviceDictionaryRWItem>
    <DeviceDictionaryRWItem>
      <Bits>16</Bits>
      <Use>false</Use>
      <Name>Параметр 248</Name>
      <ShowFunction>ShowUInt</ShowFunction>
      <ParseFunction>ParseUInt</ParseFunction>
    </DeviceDictionaryRWItem>
    <DeviceDictionaryRWItem>
      <Bits>16</Bits>
      <Use>false</Use>
      <Name>Параметр 249</Name>
      <ShowFunction>ShowUInt</ShowFunction>
      <ParseFunction>ParseUInt</ParseFunction>
    </DeviceDictionaryRWItem>
    <DeviceDictionaryRWItem>
      <Bits>16</Bits>
      <Use>false</Use>
      <Name>Параметр 250</Name>
      <ShowFunction>ShowUInt</ShowFunction>
      <ParseFunction>ParseUInt</ParseFunction>
    </DeviceDictionaryRWItem>
    <DeviceDictionaryRWItem>
      <Bits>16</Bits>
      <Use>false</Use>
      <Name>Параметр 251</Name>
      <ShowFunction>ShowUInt</ShowFunction>
      <ParseFunction>ParseUInt</ParseFunction>
    </DeviceDictionaryRWItem>
    <DeviceDictionaryRWItem>
      <Bits>16</Bits>
      <Use>false</Use>
      <Name>Параметр 252</Name>
      <ShowFunction>ShowUInt</ShowFunction>
      <ParseFunction>ParseUInt</ParseFunction>
    </DeviceDictionaryRWItem>
    <DeviceDictionaryRWItem>
      <Bits>16</Bits>
      <Use>false</Use>
      <Name>Параметр 253</Name>
      <ShowFunction>ShowUInt</ShowFunction>
      <ParseFunction>ParseUInt</ParseFunction>
    </DeviceDictionaryRWItem>
    <DeviceDictionaryRWItem>
      <Bits>16</Bits>
      <Use>false</Use>
      <Name>Параметр 254</Name>
      <ShowFunction>ShowUInt</ShowFunction>
      <ParseFunction>ParseUInt</ParseFunction>
    </DeviceDictionaryRWItem>
    <DeviceDictionaryRWItem>
      <Bits>16</Bits>
      <Use>false</Use>
      <Name>Параметр 255</Name>
      <ShowFunction>ShowUInt</ShowFunction>
      <ParseFunction>ParseUInt</ParseFunction>
    </DeviceDictionaryRWItem>
  </RWFlashItems>
</DeviceDictionary>





